MANIFEST.in
README.rst
setup.py
pytlas/__about__.py
pytlas/__init__.py
pytlas/datautils.py
pytlas/ioutils.py
pytlas/pkgutils.py
pytlas/settings.py
pytlas/store.py
pytlas.egg-info/PKG-INFO
pytlas.egg-info/SOURCES.txt
pytlas.egg-info/dependency_links.txt
pytlas.egg-info/entry_points.txt
pytlas.egg-info/requires.txt
pytlas.egg-info/top_level.txt
pytlas/cli/__init__.py
pytlas/cli/prompt.py
pytlas/cli/utils.py
pytlas/conversing/__init__.py
pytlas/conversing/agent.py
pytlas/conversing/request.py
pytlas/handling/__init__.py
pytlas/handling/card.py
pytlas/handling/hooks.py
pytlas/handling/importers.py
pytlas/handling/localization.py
pytlas/handling/skill.py
pytlas/supporting/__init__.py
pytlas/supporting/manager.py
pytlas/testing/__init__.py
pytlas/testing/attrdict.py
pytlas/testing/factory.py
pytlas/testing/mock.py
pytlas/understanding/__init__.py
pytlas/understanding/intent.py
pytlas/understanding/interpreter.py
pytlas/understanding/slot.py
pytlas/understanding/snips.py
pytlas/understanding/training.py
tests/__init__.py
tests/test_datautils.py
tests/test_ioutils.py
tests/test_pkgutils.py
tests/test_settings.py
tests/test_store.py
tests/conversing/__init__.py
tests/conversing/test_agent.py
tests/conversing/test_agent_context.py
tests/conversing/test_agent_utils.py
tests/conversing/test_request.py
tests/handling/__init__.py
tests/handling/test_card.py
tests/handling/test_hooks.py
tests/handling/test_importers.py
tests/handling/test_localization.py
tests/handling/test_skill.py
tests/supporting/__init__.py
tests/supporting/test_manager.py
tests/testing/__init__.py
tests/testing/test_testing.py
tests/understanding/__init__.py
tests/understanding/test_intent.py
tests/understanding/test_interpreter.py
tests/understanding/test_slot_value.py
tests/understanding/test_slot_values.py
tests/understanding/test_snips.py
tests/understanding/test_training.py