Metadata-Version: 2.1
Name: pytlas
Version: 5.1.2
Summary: An open-source Python 3 assistant library built for people and made to be super easy to setup and understand!
Home-page: https://github.com/atlassistant/pytlas
Author: Julien LEICHER
Author-email: julien@leicher.me
License: GPL-3.0
Project-URL: Documentation, https://pytlas.readthedocs.io/
Project-URL: Source, https://github.com/atlassistant/pytlas
Project-URL: Tracker, https://github.com/atlassistant/pytlas/issues
Platform: UNKNOWN
Classifier: Programming Language :: Python :: 3
Provides-Extra: docs
Provides-Extra: watch
Provides-Extra: snips
Provides-Extra: test
